NsparkleLog/Interfaces.py
NsparkleLog/__init__.py
NsparkleLog/_env.py
NsparkleLog/all.py
NsparkleLog/dependencies.py
NsparkleLog/egg.py
NsparkleLog/metadata.py
NsparkleLog/core/__init__.py
NsparkleLog/core/_excformat.py
NsparkleLog/core/_formatter.py
NsparkleLog/core/_handler.py
NsparkleLog/core/_level.py
NsparkleLog/core/_logger.py
NsparkleLog/core/_manager.py
NsparkleLog/core/_record.py
NsparkleLog/plugins/__init__.py
NsparkleLog/plugins/helpers.py
NsparkleLog/utils/__init__.py
NsparkleLog/utils/_color.py
NsparkleLog/utils/_get_lock.py
NsparkleLog/utils/_types.py
NsparkleLog-1.1.8.dist-info/LICENSE
NsparkleLog-1.1.8.dist-info/METADATA
NsparkleLog-1.1.8.dist-info/WHEEL
NsparkleLog-1.1.8.dist-info/top_level.txt
NsparkleLog-1.1.8.dist-info/RECORD
