Metadata-Version: 2.1
Name: NsparkleLog
Version: 1.1.8
Summary: A useful logging library for Python
Home-page: https://github.com/KOKOMI12345/NewSparkleLogging
Author: 花火official
Author-email: 3072252442@qq.com
License: MIT
Classifier: Programming Language :: Python :: 3
Classifier: License :: OSI Approved :: MIT License
Classifier: Operating System :: OS Independent
License-File: LICENSE
